ai_forensics/__init__.py
ai_forensics/__main__.py
ai_forensics/ascii.py
ai_forensics/cli.py
aiforensics-0.0.0.dist-info/entry_points.txt
aiforensics-0.0.0.dist-info/LICENSE
aiforensics-0.0.0.dist-info/METADATA
aiforensics-0.0.0.dist-info/WHEEL
aiforensics-0.0.0.dist-info/RECORD
