Metadata-Version: 2.3
Name: aiforensics
Version: 0.0.0
Summary: Command-line tool for inspecting AI/ML models.
License: MIT
Author: interwebshack
Author-email: 22042209+interwebshack@users.noreply.github.com
Requires-Python: >=3.10,<4.0
Classifier: License :: OSI Approved :: MIT License
Classifier: Programming Language :: Python :: 3
Classifier: Programming Language :: Python :: 3.10
Classifier: Programming Language :: Python :: 3.11
Classifier: Programming Language :: Python :: 3.12
Classifier: Programming Language :: Python :: 3.13
Requires-Dist: rich (>=14.0.0,<15.0.0)
